test_bmi.py
test_bmi-1.0.dist-info/METADATA
test_bmi-1.0.dist-info/WHEEL
test_bmi-1.0.dist-info/entry_points.txt
test_bmi-1.0.dist-info/top_level.txt
test_bmi-1.0.dist-info/RECORD
